{
  "version": "0.2",
  "language": "en",
  "useGitignore": true,
  "ignorePaths": [
    "target",
    "Cargo.lock",
    "**/*.png",
    "**/*.jpg",
    "**/*.jpeg",
    "**/*.gif",
    "**/*.svg",
    "**/*.pdf",
    "**/*.zip"
  ],
  "words": [
    "anyhow",
    "binarycookies",
    "brotli",
    "clippy",
    "codegen",
    "curl",
    "DPAPI",
    "httpmock",
    "ionide",
    "macos",
    "Miri",
    "MSRV",
    "MSVC",
    "pemfile",
    "PMBOK",
    "redirs",
    "reimplementation",
    "reqwest",
    "rurl",
    "rustc",
    "RUSTFLAGS",
    "rustfmt",
    "rustls",
    "rustup",
    "serde",
    "tempfile",
    "thiserror",
    "tokio",
    "winapi",
    "wincrypt",
    "winuser",
    "xattr"
  ],
  "ignoreRegExpList": [
    "yt-dlp"
  ]
}
